Metadata-Version: 1.1
Name: cin_term3
Version: 0.0.3
Summary: In this version of cin_term, you can do many things, check the commands and syntax in github.com/RgTheGreat/cin_term
Home-page: UNKNOWN
Author: Rigved Aneesh
Author-email: rigved.bob@gmail.com
License: UNKNOWN
Keywords: cin_term3,terminal
Platform: UNKNOWN
Classifier: Development Status :: 3 - Alpha
Classifier: Intended Audience :: Education
Classifier: Programming Language :: Python :: 3
